skmob/__init__.py
skmob/core/__init__.py
skmob/core/flowdataframe.py
skmob/core/tests/__init__.py
skmob/core/tests/test_flowdataframe.py
skmob/core/tests/test_skmob_release.py
skmob/core/tests/test_trajectorydataframe.py
skmob/core/trajectorydataframe.py
skmob/data/__init__.py
skmob/data/datasets/__init__.py
skmob/data/datasets/example_dps.py
skmob/data/datasets/flow_foursquare_nyc/flow_foursquare_nyc.json
skmob/data/datasets/flow_foursquare_nyc/flow_foursquare_nyc.py
skmob/data/datasets/foursquare_nyc/foursquare_nyc.json
skmob/data/datasets/foursquare_nyc/foursquare_nyc.py
skmob/data/datasets/nyc_boundaries/nyc_boundaries.json
skmob/data/datasets/nyc_boundaries/nyc_boundaries.py
skmob/data/datasets/parking_san_francisco/parking_san_francisco.json
skmob/data/datasets/parking_san_francisco/parking_san_francisco.py
skmob/data/datasets/taxi_san_francisco/taxi_san_francisco.json
skmob/data/datasets/taxi_san_francisco/taxi_san_francisco.py
skmob/data/load.py
skmob/data/tests/__init__.py
skmob/data/tests/test_datamodule.py
skmob/io/__init__.py
skmob/io/file.py
skmob/io/tests/__init__.py
skmob/measures/__init__.py
skmob/measures/collective.py
skmob/measures/evaluation.py
skmob/measures/individual.py
skmob/measures/tests/__init__.py
skmob/measures/tests/test_collective.py
skmob/measures/tests/test_evaluation.py
skmob/measures/tests/test_individual.py
skmob/models/__init__.py
skmob/models/epr.py
skmob/models/geosim.py
skmob/models/gravity.py
skmob/models/markov_diary_generator.py
skmob/models/radiation.py
skmob/models/sts_epr.py
skmob/models/tests/__init__.py
skmob/models/tests/test_epr.py
skmob/models/tests/test_geosim.py
skmob/models/tests/test_gravity.py
skmob/models/tests/test_radiation.py
skmob/models/tests/test_sts_epr.py
skmob/preprocessing/__init__.py
skmob/preprocessing/clustering.py
skmob/preprocessing/compression.py
skmob/preprocessing/detection.py
skmob/preprocessing/enrichment.py
skmob/preprocessing/filtering.py
skmob/preprocessing/routing.py
scikit_mobility-1.3.1.dist-info/LICENSE
scikit_mobility-1.3.1.dist-info/WHEEL
scikit_mobility-1.3.1.dist-info/METADATA
scikit_mobility-1.3.1.dist-info/RECORD
