Metadata-Version: 2.1
Name: scikit-mobility
Version: 1.3.1
Summary: A toolbox for analyzing and processing mobility data.
License: new BSD
Author: skmob Developers
Maintainer: Gianni Barlacchi
Maintainer-email: gianni.barlacchi@gmail.com
Requires-Python: >=3.8,<4
Classifier: Intended Audience :: Developers
Classifier: Intended Audience :: Science/Research
Classifier: License :: OSI Approved
Classifier: License :: OSI Approved :: BSD License
Classifier: License :: Other/Proprietary License
Classifier: Operating System :: MacOS
Classifier: Operating System :: Microsoft :: Windows
Classifier: Operating System :: Unix
Classifier: Programming Language :: Python
Classifier: Programming Language :: Python :: 3
Classifier: Programming Language :: Python :: 3.10
Classifier: Programming Language :: Python :: 3.6
Classifier: Programming Language :: Python :: 3.7
Classifier: Programming Language :: Python :: 3.8
Classifier: Programming Language :: Python :: 3.9
Classifier: Topic :: Scientific/Engineering
Classifier: Topic :: Software Development
Requires-Dist: folium (==0.12.1.post1)
Requires-Dist: geojson (>=2.5.0,<3.0.0)
Requires-Dist: geopandas (>=0.10.2,<0.11.0)
Requires-Dist: h3 (>=3.7.3,<4.0.0)
Requires-Dist: pandas (>=1.1.5,<2.0.0)
Requires-Dist: pooch (>=1.6.0,<2.0.0)
Requires-Dist: powerlaw (>=1.4.6,<2.0.0)
Requires-Dist: python-igraph (>=0.9.1,<0.10.0)
Requires-Dist: requests (>=2.25.1,<3.0.0)
Requires-Dist: scikit-learn
Requires-Dist: statsmodels (>=0.13.0,<0.14.0)
Requires-Dist: tqdm (>=4.60.0,<5.0.0)
Project-URL: Documentation, https://scikit-mobility.github.io/scikit-mobility
